CHANGES.txt
LICENSE.txt
MANIFEST.in
README.txt
setup.py
js/__init__.py
js.bootstrap_switch.egg-info/PKG-INFO
js.bootstrap_switch.egg-info/SOURCES.txt
js.bootstrap_switch.egg-info/dependency_links.txt
js.bootstrap_switch.egg-info/entry_points.txt
js.bootstrap_switch.egg-info/namespace_packages.txt
js.bootstrap_switch.egg-info/not-zip-safe
js.bootstrap_switch.egg-info/requires.txt
js.bootstrap_switch.egg-info/top_level.txt
js/bootstrap_switch/__init__.py
js/bootstrap_switch/test_bootstrap_switch.txt
js/bootstrap_switch/resources/css/bootstrap-switch.css
js/bootstrap_switch/resources/css/bootstrap-switch.min.css
js/bootstrap_switch/resources/js/bootstrap-switch.js
js/bootstrap_switch/resources/js/bootstrap-switch.min.js