Metadata-Version: 1.0
Name: js.bootstrap-switch
Version: 3.3.2
Summary: Fanstatic packaging of Bootstrap Switch
Home-page: UNKNOWN
Author: Fanstatic Developers
Author-email: fanstatic@googlegroups.com
License: BSD
Platform: UNKNOWN
